jupyterlab_zenodo/__init__.py
jupyterlab_zenodo/_version.py
jupyterlab_zenodo/base.py
jupyterlab_zenodo/config.py
jupyterlab_zenodo/database.py
jupyterlab_zenodo/status.py
jupyterlab_zenodo/test_init.py
jupyterlab_zenodo/update.py
jupyterlab_zenodo/upload.py
jupyterlab_zenodo/utils.py
jupyterlab_zenodo/zenodo.py
jupyterlab_zenodo/tests/__init__.py
jupyterlab_zenodo/tests/test_client.py
jupyterlab_zenodo/tests/test_database.py
jupyterlab_zenodo/tests/test_deposition.py
jupyterlab_zenodo/tests/test_upload.py
jupyterlab_zenodo/tests/test_utils.py
jupyterlab_zenodo-0.0.2.data/data/etc/jupyter/jupyter_notebook_config.d/jupyterlab_zenodo.json
jupyterlab_zenodo-0.0.2.dist-info/METADATA
jupyterlab_zenodo-0.0.2.dist-info/WHEEL
jupyterlab_zenodo-0.0.2.dist-info/top_level.txt
jupyterlab_zenodo-0.0.2.dist-info/RECORD
