Metadata-Version: 2.1
Name: jupyterlab-zenodo
Version: 0.0.2
Summary: A Jupyter Notebook extension which enables uploading to Zenodo from JupyterLab
Home-page: https://github.com/chameleoncloud/jupyterlab-zenodo
Author: University of Chicago
Author-email: dev@chameleoncloud.org
License: BSD
Keywords: jupyter,jupyterlab,openstack,zenodo
Platform: Linux
Platform: Mac OS X
Platform: Windows
Classifier: Intended Audience :: Developers
Classifier: Intended Audience :: System Administrators
Classifier: Intended Audience :: Science/Research
Classifier: License :: OSI Approved :: BSD License
Classifier: Programming Language :: Python
Classifier: Programming Language :: Python :: 3
Requires-Dist: notebook (>=4.3.0)
Requires-Dist: python-slugify (>=3.0.3)
